{
    "ul": [
        {
            "li": "Увеличить номинал, но не изменять количество костей."
        },
        {
            "li": "Увеличить количество костей - номинал может быть любым."
        },
        {
            "li": "«уйти в единицы» - сделать ход только на единицы, ориентируясь (пытаясь угадать) только количество единиц у всех игроков. При этом количество костей в ходе может составлять минимум половину костей ставки предыдущего игрока, если это было четное число. При нечетном количестве костей в ставке предыдущего игрока, происходит округление в большую сторону."
        },
        {
            "li": "Игрок, делающий ход после «ушедшего в единицы», может:",
            "ul": [
                {
                    "li": "увеличить количество костей «в единицах»"
                },
                {
                    "li": "сделать ход в другом номинале, но с количеством костей на одну больше, чем двойное число ставки в единицах предыдущего игрока"
                }
            ]
        }
    ]
}
